{
    "0": {
        "specifications": {
            "0": {
                "name": "Method",
                "value": "Scan2CAD [4]"
            }
        },
        "Measure": "Online",
        "Outcome": "nan"
    },
    "1": {
        "specifications": {
            "0": {
                "name": "Method",
                "value": "Scan2CAD [4]"
            }
        },
        "Measure": "Cls avg.",
        "Outcome": "31.7"
    },
    "2": {
        "specifications": {
            "0": {
                "name": "Method",
                "value": "Scan2CAD [4]"
            }
        },
        "Measure": "Cabinet",
        "Outcome": "34.0"
    },
    "3": {
        "specifications": {
            "0": {
                "name": "Method",
                "value": "Scan2CAD [4]"
            }
        },
        "Measure": "Chair",
        "Outcome": "44.3"
    },
    "4": {
        "specifications": {
            "0": {
                "name": "Method",
                "value": "Scan2CAD [4]"
            }
        },
        "Measure": "Display",
        "Outcome": "17.9"
    },
    "5": {
        "specifications": {
            "0": {
                "name": "Method",
                "value": "Scan2CAD [4]"
            }
        },
        "Measure": "Table",
        "Outcome": "30.7"
    },
    "6": {
        "specifications": {
            "0": {
                "name": "Method",
                "value": "RayTran [34]"
            }
        },
        "Measure": "Online",
        "Outcome": "nan"
    },
    "7": {
        "specifications": {
            "0": {
                "name": "Method",
                "value": "RayTran [34]"
            }
        },
        "Measure": "Cls avg.",
        "Outcome": "42.1"
    },
    "8": {
        "specifications": {
            "0": {
                "name": "Method",
                "value": "RayTran [34]"
            }
        },
        "Measure": "Cabinet",
        "Outcome": "36.2"
    },
    "9": {
        "specifications": {
            "0": {
                "name": "Method",
                "value": "RayTran [34]"
            }
        },
        "Measure": "Chair",
        "Outcome": "59.3"
    },
    "10": {
        "specifications": {
            "0": {
                "name": "Method",
                "value": "RayTran [34]"
            }
        },
        "Measure": "Display",
        "Outcome": "30.4"
    },
    "11": {
        "specifications": {
            "0": {
                "name": "Method",
                "value": "RayTran [34]"
            }
        },
        "Measure": "Table",
        "Outcome": "42.5"
    },
    "12": {
        "specifications": {
            "0": {
                "name": "Method",
                "value": "Vid2CAD [24]"
            }
        },
        "Measure": "Online",
        "Outcome": "\u2713"
    },
    "13": {
        "specifications": {
            "0": {
                "name": "Method",
                "value": "Vid2CAD [24]"
            }
        },
        "Measure": "Cls avg.",
        "Outcome": "38.8"
    },
    "14": {
        "specifications": {
            "0": {
                "name": "Method",
                "value": "Vid2CAD [24]"
            }
        },
        "Measure": "Cabinet",
        "Outcome": "23.8"
    },
    "15": {
        "specifications": {
            "0": {
                "name": "Method",
                "value": "Vid2CAD [24]"
            }
        },
        "Measure": "Chair",
        "Outcome": "64.6"
    },
    "16": {
        "specifications": {
            "0": {
                "name": "Method",
                "value": "Vid2CAD [24]"
            }
        },
        "Measure": "Display",
        "Outcome": "37.7"
    },
    "17": {
        "specifications": {
            "0": {
                "name": "Method",
                "value": "Vid2CAD [24]"
            }
        },
        "Measure": "Table",
        "Outcome": "28.9"
    },
    "18": {
        "specifications": {
            "0": {
                "name": "Method",
                "value": "ELLIPSDF [30]"
            }
        },
        "Measure": "Online",
        "Outcome": "\u2713"
    },
    "19": {
        "specifications": {
            "0": {
                "name": "Method",
                "value": "ELLIPSDF [30]"
            }
        },
        "Measure": "Cls avg.",
        "Outcome": "39.6"
    },
    "20": {
        "specifications": {
            "0": {
                "name": "Method",
                "value": "ELLIPSDF [30]"
            }
        },
        "Measure": "Cabinet",
        "Outcome": "-"
    },
    "21": {
        "specifications": {
            "0": {
                "name": "Method",
                "value": "ELLIPSDF [30]"
            }
        },
        "Measure": "Chair",
        "Outcome": "-"
    },
    "22": {
        "specifications": {
            "0": {
                "name": "Method",
                "value": "ELLIPSDF [30]"
            }
        },
        "Measure": "Display",
        "Outcome": "-"
    },
    "23": {
        "specifications": {
            "0": {
                "name": "Method",
                "value": "ELLIPSDF [30]"
            }
        },
        "Measure": "Table",
        "Outcome": "-"
    },
    "24": {
        "specifications": {
            "0": {
                "name": "Method",
                "value": "TransPoser"
            }
        },
        "Measure": "Online",
        "Outcome": "\u2713"
    },
    "25": {
        "specifications": {
            "0": {
                "name": "Method",
                "value": "TransPoser"
            }
        },
        "Measure": "Cls avg.",
        "Outcome": "59.3"
    },
    "26": {
        "specifications": {
            "0": {
                "name": "Method",
                "value": "TransPoser"
            }
        },
        "Measure": "Cabinet",
        "Outcome": "45.4"
    },
    "27": {
        "specifications": {
            "0": {
                "name": "Method",
                "value": "TransPoser"
            }
        },
        "Measure": "Chair",
        "Outcome": "91.2"
    },
    "28": {
        "specifications": {
            "0": {
                "name": "Method",
                "value": "TransPoser"
            }
        },
        "Measure": "Display",
        "Outcome": "45.0"
    },
    "29": {
        "specifications": {
            "0": {
                "name": "Method",
                "value": "TransPoser"
            }
        },
        "Measure": "Table",
        "Outcome": "55.7"
    }
}